.gitignore
LICENSE.txt
README.txt
setup.py
tweetworks/API.py
tweetworks/Group.py
tweetworks/Post.py
tweetworks/User.py
tweetworks/__init__.py
tweetworks.egg-info/PKG-INFO
tweetworks.egg-info/SOURCES.txt
tweetworks.egg-info/dependency_links.txt
tweetworks.egg-info/requires.txt
tweetworks.egg-info/top_level.txt