Metadata-Version: 1.0
Name: tweetworks
Version: 1.0.0b1
Summary: Python bindings for the tweetworks.com web service API
Home-page: http://www.ultranurd.net/code/tweetworks/
Author: Nicolas Ward
Author-email: ultranurd@yahoo.com
License: GPL
Platform: UNKNOWN
